keyin_plm.py
keyin_plm-0.0.2.dist-info/METADATA
keyin_plm-0.0.2.dist-info/WHEEL
keyin_plm-0.0.2.dist-info/top_level.txt
keyin_plm-0.0.2.dist-info/RECORD
