Metadata-Version: 2.1
Name: keyin-plm
Version: 0.0.2
Summary: UNKNOWN
Home-page: UNKNOWN
Author: yangfan
License: MIT
Platform: UNKNOWN
Requires-Python: >=3
Requires-Dist: requests-toolbelt (>=0.9.1)
